maixhub/__init__.py
maixhub-0.0.1.dist-info/LICENSE
maixhub-0.0.1.dist-info/METADATA
maixhub-0.0.1.dist-info/WHEEL
maixhub-0.0.1.dist-info/entry_points.txt
maixhub-0.0.1.dist-info/top_level.txt
maixhub-0.0.1.dist-info/RECORD
