Metadata-Version: 2.1
Name: maixhub
Version: 0.0.1
Summary: maixhub python toolkit
Home-page: https://maixhub.com
Author: Neucrack
Author-email: CZD666666@gmail.com
License: MIT
Keywords: maixhub ai
Platform: UNKNOWN
Classifier: Intended Audience :: Developers
Classifier: License :: OSI Approved :: MIT License
Classifier: Programming Language :: Python :: 3.7
Classifier: Programming Language :: Python :: 3.8
Classifier: Programming Language :: Python :: 3.9
Classifier: Programming Language :: Python :: 3.10
